Metadata-Version: 2.4
Name: adafruit-circuitpython-clue
Version: 3.2.5
Summary: A high-level library representing all the features of the Adafruit CLUE
Author-email: Adafruit Industries <circuitpython@adafruit.com>
License: MIT
Project-URL: Homepage, https://github.com/adafruit/Adafruit_CircuitPython_CLUE
Keywords: adafruit,clue,microbit,microcontroller,hardware,micropython,circuitpython
Classifier: Intended Audience :: Developers
Classifier: Topic :: Software Development :: Libraries
Classifier: Topic :: Software Development :: Embedded Systems
Classifier: Topic :: System :: Hardware
Classifier: License :: OSI Approved :: MIT License
Classifier: Programming Language :: Python :: 3
License-File: LICENSE
Requires-Dist: Adafruit-Blinka
Requires-Dist: adafruit-circuitpython-busdevice
Requires-Dist: adafruit-circuitpython-lsm6ds
Requires-Dist: adafruit-circuitpython-display-text
Requires-Dist: adafruit-circuitpython-register
Requires-Dist: adafruit-circuitpython-neopixel
Requires-Dist: adafruit-circuitpython-sht31d
Requires-Dist: adafruit-circuitpython-bmp280
Requires-Dist: adafruit-circuitpython-lis3mdl
Requires-Dist: adafruit-circuitpython-apds9960
Provides-Extra: optional
Dynamic: license-file
